ironic_ui/__init__.py
ironic_ui/karma.conf.js
ironic_ui/api/__init__.py
ironic_ui/api/ironic.py
ironic_ui/api/ironic_rest_api.py
ironic_ui/content/__init__.py
ironic_ui/content/ironic/__init__.py
ironic_ui/content/ironic/panel.py
ironic_ui/content/ironic/urls.py
ironic_ui/content/ironic/views.py
ironic_ui/content/ironic/templates/ironic/index.html
ironic_ui/content/ironic/templates/ironic/node_detail.html
ironic_ui/enabled/_2200_ironic.py
ironic_ui/enabled/__init__.py
ironic_ui/locale/de/LC_MESSAGES/django.po
ironic_ui/locale/de/LC_MESSAGES/djangojs.po
ironic_ui/locale/en_GB/LC_MESSAGES/django.po
ironic_ui/locale/en_GB/LC_MESSAGES/djangojs.po
ironic_ui/locale/fr/LC_MESSAGES/djangojs.po
ironic_ui/locale/id/LC_MESSAGES/django.po
ironic_ui/locale/id/LC_MESSAGES/djangojs.po
ironic_ui/locale/ja/LC_MESSAGES/djangojs.po
ironic_ui/locale/ko_KR/LC_MESSAGES/django.po
ironic_ui/locale/ko_KR/LC_MESSAGES/djangojs.po
ironic_ui/locale/pt_BR/LC_MESSAGES/djangojs.po
ironic_ui/locale/ru/LC_MESSAGES/django.po
ironic_ui/locale/ru/LC_MESSAGES/djangojs.po
ironic_ui/locale/tr_TR/LC_MESSAGES/djangojs.po
ironic_ui/locale/zh_Hans/LC_MESSAGES/django.po
ironic_ui/locale/zh_Hans/LC_MESSAGES/djangojs.po
ironic_ui/static/dashboard/admin/ironic/auto-focus.directive.js
ironic_ui/static/dashboard/admin/ironic/driver-property.service.js
ironic_ui/static/dashboard/admin/ironic/driver-property.service.spec.js
ironic_ui/static/dashboard/admin/ironic/empty-to-pristine.directive.js
ironic_ui/static/dashboard/admin/ironic/form-field.directive.js
ironic_ui/static/dashboard/admin/ironic/form-field.html
ironic_ui/static/dashboard/admin/ironic/form-field.service.js
ironic_ui/static/dashboard/admin/ironic/form-field.service.spec.js
ironic_ui/static/dashboard/admin/ironic/graph.service.js
ironic_ui/static/dashboard/admin/ironic/ironic.backend-mock.service.js
ironic_ui/static/dashboard/admin/ironic/ironic.module.js
ironic_ui/static/dashboard/admin/ironic/ironic.service.js
ironic_ui-6.6.0.dist-info/AUTHORS
ironic_ui-6.6.0.dist-info/LICENSE
ironic_ui-6.6.0.dist-info/METADATA
ironic_ui-6.6.0.dist-info/WHEEL
ironic_ui-6.6.0.dist-info/pbr.json
ironic_ui-6.6.0.dist-info/top_level.txt
ironic_ui-6.6.0.dist-info/RECORD
